logicexp/__init__.py
logicexp-0.0.3.dist-info/LICENSE
logicexp-0.0.3.dist-info/METADATA
logicexp-0.0.3.dist-info/WHEEL
logicexp-0.0.3.dist-info/top_level.txt
logicexp-0.0.3.dist-info/RECORD
