Metadata-Version: 2.1
Name: logicexp
Version: 0.0.3
Summary: A package to help calculate the result of a logical expression
Home-page: https://github.com/kirtish16/logicexp
Author: Kirtish Surangalikar
Author-email: kirtishSurangalikar@protonmail.com
License: UNKNOWN
Project-URL: Bug Tracker, https://github.com/kirtish16/logicexp/issues
Platform: UNKNOWN
Classifier: Programming Language :: Python :: 3
Classifier: License :: OSI Approved :: MIT License
Classifier: Operating System :: OS Independent
Requires-Python: >=3.6
License-File: LICENSE
